nomnomdata/engine/__init__.py
nomnomdata/engine/components.py
nomnomdata/engine/connections.py
nomnomdata/engine/encoders.py
nomnomdata/engine/engine.py
nomnomdata/engine/errors.py
nomnomdata/engine/globals.py
nomnomdata/engine/logging.py
nomnomdata/engine/nominode.py
nomnomdata/engine/parameters.py
nomnomdata/engine/shared_configs.py
nomnomdata/engine/testing.py
nomnomdata/engine/util.py
nomnomdata_engine-2.0.32.dist-info/METADATA
nomnomdata_engine-2.0.32.dist-info/WHEEL
nomnomdata_engine-2.0.32.dist-info/licenses/COPYING
nomnomdata_engine-2.0.32.dist-info/licenses/COPYING.LESSER
nomnomdata_engine-2.0.32.dist-info/licenses/LICENSE
nomnomdata_engine-2.0.32.dist-info/RECORD
