Metadata-Version: 2.4
Name: nomnomdata-engine
Version: 2.0.32
Summary: Package containing tooling for developing nominode engines
License: LGPL-3.0-only
License-File: COPYING
License-File: COPYING.LESSER
License-File: LICENSE
Author: Nom Nom Data Inc
Author-email: info@nomnomdata.com
Requires-Python: >=3.9,<4.0
Classifier: License :: OSI Approved :: GNU Lesser General Public License v3 (LGPLv3)
Classifier: Programming Language :: Python :: 3
Classifier: Programming Language :: Python :: 3.9
Classifier: Programming Language :: Python :: 3.10
Classifier: Programming Language :: Python :: 3.11
Classifier: Programming Language :: Python :: 3.12
Classifier: Programming Language :: Python :: 3.13
Classifier: Programming Language :: Python :: 3.14
Requires-Dist: click (>=8.1.7,<9.0.0)
Requires-Dist: dunamai (>=1.21.1,<2.0.0)
Requires-Dist: httmock (>=1.4.0,<2.0.0)
Requires-Dist: pyyaml (>=6.0.1,<7.0.0)
Requires-Dist: requests (>=2.32.3,<3.0.0)
Requires-Dist: wrapt (>=1.16.0,<2.0.0)
Project-URL: Repository, https://gitlab.com/nomnomdata/tools/nomnomdata-engine
